qibolab_qm/__init__.py
qibolab_qm-0.0.1.dist-info/LICENSE
qibolab_qm-0.0.1.dist-info/METADATA
qibolab_qm-0.0.1.dist-info/WHEEL
qibolab_qm-0.0.1.dist-info/RECORD
