Metadata-Version: 2.3
Name: qibolab-qm
Version: 0.0.1
Summary: Quantum hardware module and drivers for Qibo
License: Apache-2.0
Author: The Qibo team
Requires-Python: >=3.9,<3.13
Classifier: License :: OSI Approved :: Apache Software License
Classifier: Programming Language :: Python :: 3
Classifier: Programming Language :: Python :: 3.9
Classifier: Programming Language :: Python :: 3.10
Classifier: Programming Language :: Python :: 3.11
Classifier: Programming Language :: Python :: 3.12
Classifier: Topic :: Scientific/Engineering :: Physics
Requires-Dist: qibolab (>=0.2.6,<0.3.0)
Requires-Dist: qm-qua (==1.2.1)
Project-URL: Documentation, https://qibo.science/docs/qibolab-qm/stable
Project-URL: Homepage, https://qibo.science/
Project-URL: Repository, https://github.com/qiboteam/qibolab-qm/
